wbx_cpl/__init__.py
wbx_cpl/__main__.py
wbx_cpl/dataframe.py
wbx_cpl/utils.py
wbx_cpl/wbx.py
wbx_cpl-1.3.2.dist-info/METADATA
wbx_cpl-1.3.2.dist-info/WHEEL
wbx_cpl-1.3.2.dist-info/licenses/LICENSE
wbx_cpl-1.3.2.dist-info/RECORD
