Metadata-Version: 2.3
Name: wbx-cpl
Version: 1.3.2
Summary: Commands for Webex Compliance Officers
Author-email: Stephane Cohen <stecohen@gmail.com>
License: MIT License
License-File: LICENSE
Keywords: Compliance,Control Hub,Webex
Classifier: License :: OSI Approved :: MIT License
Classifier: Programming Language :: Python
Classifier: Programming Language :: Python :: 3
Requires-Python: >=3.10
Requires-Dist: click==8.1.7
Requires-Dist: pandas==2.1.4
Requires-Dist: requests==2.31.0
